sparktype/__init__.py
sparktype/cli.py
sparktype/bin/sparktype
sparktype-0.1.0.dist-info/METADATA
sparktype-0.1.0.dist-info/WHEEL
sparktype-0.1.0.dist-info/entry_points.txt
sparktype-0.1.0.dist-info/top_level.txt
sparktype-0.1.0.dist-info/RECORD
