Metadata-Version: 2.4
Name: sparktype
Version: 0.1.0
Summary: Generate static types from OpenAPI specifications
Author: hntrl
License: MIT
Project-URL: Homepage, https://github.com/hntrl/sparktype
Project-URL: Repository, https://github.com/hntrl/sparktype
Project-URL: Issues, https://github.com/hntrl/sparktype/issues
Keywords: openapi,typescript,codegen,types,schema,zod,python
Classifier: Development Status :: 4 - Beta
Classifier: Environment :: Console
Classifier: Intended Audience :: Developers
Classifier: License :: OSI Approved :: MIT License
Classifier: Operating System :: OS Independent
Classifier: Programming Language :: Python :: 3
Classifier: Programming Language :: Python :: 3.8
Classifier: Programming Language :: Python :: 3.9
Classifier: Programming Language :: Python :: 3.10
Classifier: Programming Language :: Python :: 3.11
Classifier: Programming Language :: Python :: 3.12
Classifier: Topic :: Software Development :: Code Generators
Requires-Python: >=3.8
